ticktick_v2/__init__.py
ticktick_v2/cookies_login.py
ticktick_v2/focus.py
ticktick_v2/habits.py
ticktick_v2/tasks.py
ticktick_v2/utils/config.py
ticktick_v2/utils/logger.py
ticktick_v2/utils/time_utils.py
ticktick_v2/web/__init__.py
ticktick_v2/web/api_request.py
ticktick_v2/web/cookies_handler.py
ticktick_v2/web/selenium.py
ticktick_py_v2-0.24.1.dist-info/LICENSE
ticktick_py_v2-0.24.1.dist-info/METADATA
ticktick_py_v2-0.24.1.dist-info/WHEEL
ticktick_py_v2-0.24.1.dist-info/RECORD
