Metadata-Version: 2.3
Name: ticktick-py-v2
Version: 0.24.1
Summary: API wrapper for the unofficial TickTick v2 API to access Tasks, Habits and Focus Times data
Author: Oliver Stoll
Author-email: oliverstoll.berlin@gmail.com
Requires-Python: >=3.11,<4.0
Classifier: Programming Language :: Python :: 3
Classifier: Programming Language :: Python :: 3.11
Classifier: Programming Language :: Python :: 3.12
Classifier: Programming Language :: Python :: 3.13
Requires-Dist: pydantic (>=2.11.5,<3.0.0)
Requires-Dist: python-dotenv (>=1.1.0,<2.0.0)
Requires-Dist: pytz (>=2025.2,<2026.0)
Requires-Dist: pyyaml (>=6.0.2,<7.0.0)
Requires-Dist: selenium (>=4.32.0,<5.0.0)
Requires-Dist: undetected-chromedriver (>=3.5.5,<4.0.0)
Requires-Dist: webdriver-manager (>=4.0.2,<5.0.0)
